countess/__init__.py
countess/py.typed
countess/core/__init__.py
countess/core/cmd.py
countess/core/config.py
countess/core/parameters.py
countess/core/pipeline.py
countess/core/plugins.py
countess/gui/__init__.py
countess/gui/config.py
countess/gui/main.py
countess/gui/mini_browser.py
countess/gui/tabular.py
countess/gui/tree.py
countess/gui/widgets.py
countess/gui/icons/add.gif
countess/gui/icons/check.gif
countess/gui/icons/countess.gif
countess/gui/icons/del.gif
countess/gui/icons/file_dir.gif
countess/gui/icons/file_file.gif
countess/gui/icons/file_up.gif
countess/gui/icons/hbar.gif
countess/gui/icons/info.gif
countess/gui/icons/redbar.gif
countess/gui/icons/sort_dn.gif
countess/gui/icons/sort_un.gif
countess/gui/icons/sort_up.gif
countess/gui/icons/uncheck.gif
countess/gui/icons/vbar.gif
countess/plugins/__init__.py
countess/plugins/columns.py
countess/plugins/correlation.py
countess/plugins/csv.py
countess/plugins/data_table.py
countess/plugins/expression.py
countess/plugins/fastq.py
countess/plugins/frequency.py
countess/plugins/group_by.py
countess/plugins/join.py
countess/plugins/mutagenize.py
countess/plugins/pivot.py
countess/plugins/python.py
countess/plugins/ranking.py
countess/plugins/regex.py
countess/plugins/score.py
countess/plugins/score_scale.py
countess/plugins/unpivot.py
countess/plugins/vampseq.py
countess/plugins/variant.py
countess/utils/__init__.py
countess/utils/duckdb.py
countess/utils/pyarrow.py
countess/utils/variant.py
countess-0.1.13.dist-info/licenses/LICENSE.txt
countess-0.1.13.dist-info/METADATA
countess-0.1.13.dist-info/WHEEL
countess-0.1.13.dist-info/entry_points.txt
countess-0.1.13.dist-info/top_level.txt
countess-0.1.13.dist-info/RECORD
