Metadata-Version: 2.4
Name: countess
Version: 0.1.13
Summary: CountESS
Author-email: Nick Moore <nick@zoic.org>, Alan Rubin <alan@rubin.id.au>
Maintainer-email: Nick Moore <nick@zoic.org>
Classifier: Development Status :: 3 - Alpha
Classifier: Intended Audience :: Science/Research
Classifier: Operating System :: OS Independent
Classifier: Topic :: Scientific/Engineering :: Bio-Informatics
Requires-Python: >=3.10
License-File: LICENSE.txt
Requires-Dist: duckdb~=1.3.1
Requires-Dist: fqfa~=1.3.1
Requires-Dist: more_itertools~=10.7.0
Requires-Dist: numpy~=2.2.6
Requires-Dist: oxbow~=0.5.1
Requires-Dist: pandas~=2.3.0
Requires-Dist: psutil~=7.0.0
Requires-Dist: pyarrow~=20.0.0
Requires-Dist: rapidfuzz~=3.13.0
Requires-Dist: scipy~=1.15.3
Requires-Dist: tkinterweb~=3.23.5
Requires-Dist: ttkthemes~=3.2.2
Requires-Dist: typing_extensions~=4.14.0
Provides-Extra: dev
Requires-Dist: black<24; extra == "dev"
Requires-Dist: build~=1.2.2; extra == "dev"
Requires-Dist: coverage~=7.9.1; extra == "dev"
Requires-Dist: mypy~=1.16.1; extra == "dev"
Requires-Dist: pylint~=3.3.7; extra == "dev"
Requires-Dist: semver~=3.0.2; extra == "dev"
Requires-Dist: types-psutil~=7.0.0; extra == "dev"
Requires-Dist: types-ttkthemes~=3.2.4; extra == "dev"
Requires-Dist: twine~=6.1.0; extra == "dev"
Requires-Dist: packaging~=25.0; extra == "dev"
Requires-Dist: pandas-stubs~=2.2.3; extra == "dev"
Requires-Dist: pyarrow-stubs~=20.0.0; extra == "dev"
Requires-Dist: pytest~=8.4.1; extra == "dev"
Requires-Dist: pytest-socket~=0.7.0; extra == "dev"
Requires-Dist: requests-mock~=1.12.1; extra == "dev"
Dynamic: license-file
